boofuzz/__init__.py
boofuzz/cli.py
boofuzz/cli_context.py
boofuzz/constants.py
boofuzz/data_test_case.py
boofuzz/data_test_step.py
boofuzz/event_hook.py
boofuzz/exception.py
boofuzz/fuzz_logger.py
boofuzz/fuzz_logger_csv.py
boofuzz/fuzz_logger_curses.py
boofuzz/fuzz_logger_db.py
boofuzz/fuzz_logger_text.py
boofuzz/fuzzable.py
boofuzz/fuzzable_block.py
boofuzz/fuzzers.py
boofuzz/helpers.py
boofuzz/ifuzz_logger.py
boofuzz/ifuzz_logger_backend.py
boofuzz/mutation.py
boofuzz/mutation_context.py
boofuzz/protocol_session.py
boofuzz/protocol_session_reference.py
boofuzz/repeater.py
boofuzz/sessions.py
boofuzz/blocks/__init__.py
boofuzz/blocks/aligned.py
boofuzz/blocks/block.py
boofuzz/blocks/checksum.py
boofuzz/blocks/repeat.py
boofuzz/blocks/request.py
boofuzz/blocks/size.py
boofuzz/connections/__init__.py
boofuzz/connections/base_socket_connection.py
boofuzz/connections/file_connection.py
boofuzz/connections/ip_constants.py
boofuzz/connections/iserial_like.py
boofuzz/connections/itarget_connection.py
boofuzz/connections/netconf_connection.py
boofuzz/connections/raw_l2_socket_connection.py
boofuzz/connections/raw_l3_socket_connection.py
boofuzz/connections/serial_connection.py
boofuzz/connections/serial_connection_low_level.py
boofuzz/connections/socket_connection.py
boofuzz/connections/ssl_socket_connection.py
boofuzz/connections/tcp_socket_connection.py
boofuzz/connections/udp_socket_connection.py
boofuzz/connections/unix_socket_connection.py
boofuzz/legos/__init__.py
boofuzz/legos/ber.py
boofuzz/legos/dcerpc.py
boofuzz/legos/misc.py
boofuzz/legos/xdr.py
boofuzz/monitors/__init__.py
boofuzz/monitors/base_monitor.py
boofuzz/monitors/callback_monitor.py
boofuzz/monitors/external_monitor.py
boofuzz/monitors/network_monitor.py
boofuzz/monitors/pedrpc.py
boofuzz/monitors/process_monitor.py
boofuzz/pgraph/__init__.py
boofuzz/pgraph/cluster.py
boofuzz/pgraph/edge.py
boofuzz/pgraph/graph.py
boofuzz/pgraph/node.py
boofuzz/primitives/__init__.py
boofuzz-0.4.1.dist-info/AUTHORS.txt
boofuzz-0.4.1.dist-info/LICENSE.txt
boofuzz-0.4.1.dist-info/METADATA
boofuzz-0.4.1.dist-info/WHEEL
boofuzz-0.4.1.dist-info/entry_points.txt
boofuzz-0.4.1.dist-info/top_level.txt
boofuzz-0.4.1.dist-info/RECORD
