Metadata-Version: 2.1
Name: boofuzz
Version: 0.4.1
Summary: A fork and successor of the Sulley Fuzzing Framework
Home-page: https://github.com/jtpereyda/boofuzz
Maintainer: Joshua Pereyda
Maintainer-email: joshua.t.pereyda@gmail.com
License: UNKNOWN
Platform: UNKNOWN
Classifier: Development Status :: 4 - Beta
Classifier: Environment :: Console
Classifier: Environment :: Console :: Curses
Classifier: Intended Audience :: Developers
Classifier: Intended Audience :: Science/Research
Classifier: License :: OSI Approved :: GNU General Public License v2 (GPLv2)
Classifier: Natural Language :: English
Classifier: Operating System :: OS Independent
Classifier: Programming Language :: Python
Classifier: Programming Language :: Python :: 3
Classifier: Programming Language :: Python :: 3.6
Classifier: Programming Language :: Python :: 3.7
Classifier: Programming Language :: Python :: 3.8
Classifier: Programming Language :: Python :: 3.9
Classifier: Programming Language :: Python :: 3.10
Classifier: Topic :: Security
Classifier: Topic :: System :: Networking
Classifier: Topic :: Software Development :: Testing :: Traffic Generation
Requires-Python: >=3.6
License-File: LICENSE.txt
License-File: AUTHORS.txt
Requires-Dist: attrs
Requires-Dist: click
Requires-Dist: colorama
Requires-Dist: Flask
Requires-Dist: funcy
Requires-Dist: future
Requires-Dist: psutil
Requires-Dist: pyserial
Requires-Dist: pydot
Requires-Dist: six
Requires-Dist: tornado
Provides-Extra: dev
Requires-Dist: black ; extra == 'dev'
Requires-Dist: tox ; extra == 'dev'
Requires-Dist: flake8 ; extra == 'dev'
Requires-Dist: check-manifest ; extra == 'dev'
Requires-Dist: mock ; extra == 'dev'
Requires-Dist: pytest ; extra == 'dev'
Requires-Dist: pytest-bdd ; extra == 'dev'
Requires-Dist: pytest-cov ; extra == 'dev'
Requires-Dist: netifaces ; extra == 'dev'
Requires-Dist: ipaddress ; extra == 'dev'
Requires-Dist: wheel ; extra == 'dev'
Requires-Dist: sphinx ; extra == 'dev'
Requires-Dist: sphinx-rtd-theme ; extra == 'dev'
Requires-Dist: pygments (>=2.4.0) ; extra == 'dev'
Provides-Extra: docs
Requires-Dist: sphinx ; extra == 'docs'
Requires-Dist: sphinx-rtd-theme ; extra == 'docs'
Requires-Dist: pygments (>=2.4.0) ; extra == 'docs'
